cba/__init__.py
cba/actuator.py
cba/consumers.py
cba/dispatcher.py
cba/exceptions.py
cba/helpers.py
cba/publishers.py
cba/commands/__init__.py
cba/commands/arguments.py
cba/commands/base_commands.py
cba/commands/commands_tools.py
cba/messages/__init__.py
cba/messages/message.py
cba/messages/messages_tools.py
cba-2.0.0.dist-info/LICENSE
cba-2.0.0.dist-info/METADATA
cba-2.0.0.dist-info/WHEEL
cba-2.0.0.dist-info/top_level.txt
cba-2.0.0.dist-info/RECORD
