Metadata-Version: 2.1
Name: cba
Version: 2.0.0
Summary: Framework for creating command interfaces for control bot
Home-page: https://github.com/osipov-andrey/control_bot_actuator
Author: Andrey Osipov
Author-email: developer.osipov@gmail.com
License: UNKNOWN
Platform: all
Classifier: License :: OSI Approved :: MIT License
Classifier: Operating System :: OS Independent
Classifier: Programming Language :: Python :: 3
Classifier: Programming Language :: Python :: Implementation :: CPython
Requires-Python: >=3.7
Requires-Dist: PyYAML (==5.3.1)
Requires-Dist: beautifulsoup4 (==4.9.3)
Requires-Dist: httpx (==0.14.3)
Requires-Dist: aioamqp (==0.14.0)
Provides-Extra: dev
Requires-Dist: pydantic (==1.7.3) ; extra == 'dev'
Requires-Dist: pytest (==6.2.2) ; extra == 'dev'
Requires-Dist: pytest-asyncio (==0.14.0) ; extra == 'dev'
Requires-Dist: pytest-mock (==3.5.1) ; extra == 'dev'
Requires-Dist: black (~=20.8b1) ; extra == 'dev'
